napari_isolate_cell/__init__.py
napari_isolate_cell/_widget.py
napari_isolate_cell/algorithms.py
napari_isolate_cell/io.py
napari_isolate_cell/napari.yaml
napari_isolate_cell/_tests/__init__.py
napari_isolate_cell/_tests/test_widget.py
napari_isolate_cell-0.1.2.dist-info/licenses/LICENSE
napari_isolate_cell-0.1.2.dist-info/METADATA
napari_isolate_cell-0.1.2.dist-info/WHEEL
napari_isolate_cell-0.1.2.dist-info/entry_points.txt
napari_isolate_cell-0.1.2.dist-info/top_level.txt
napari_isolate_cell-0.1.2.dist-info/RECORD
