Metadata-Version: 2.4
Name: napari-isolate-cell
Version: 0.1.2
Summary: Isolate soma‑specific arbors & export SWC.
Author: Sergio Bernal Garcia
Author-email: smb2318@columbia.edu
License: 
Project-URL: Homepage, https://github.com/serg-bg/napari-isolate-cell
Project-URL: Bug Tracker, https://github.com/serg-bg/napari-isolate-cell/issues
Project-URL: Documentation, https://github.com/serg-bg/napari-isolate-cell#readme
Project-URL: Source Code, https://github.com/serg-bg/napari-isolate-cell
Project-URL: Citation, https://github.com/serg-bg/napari-isolate-cell/blob/main/CITATION.cff
Keywords: napari,plugin,neuron,neuroscience,segmentation,morphology,swc,cell isolation,image analysis,3D visualization
Classifier: Development Status :: 2 - Pre-Alpha
Classifier: Framework :: napari
Classifier: Intended Audience :: Developers
Classifier: License :: OSI Approved :: BSD License
Classifier: Operating System :: OS Independent
Classifier: Programming Language :: Python
Classifier: Programming Language :: Python :: 3
Classifier: Programming Language :: Python :: 3 :: Only
Classifier: Programming Language :: Python :: 3.10
Classifier: Programming Language :: Python :: 3.11
Classifier: Programming Language :: Python :: 3.12
Classifier: Topic :: Scientific/Engineering :: Image Processing
Requires-Python: >=3.10
License-File: LICENSE
Requires-Dist: napari[all]
Requires-Dist: numpy
Requires-Dist: magicgui
Requires-Dist: qtpy
Requires-Dist: scikit-image
Requires-Dist: scipy
Requires-Dist: kimimaro
Requires-Dist: tifffile
Provides-Extra: testing
Requires-Dist: tox; extra == "testing"
Requires-Dist: pytest; extra == "testing"
Requires-Dist: pytest-cov; extra == "testing"
Requires-Dist: pytest-qt; extra == "testing"
Requires-Dist: napari; extra == "testing"
Requires-Dist: pyqt5; extra == "testing"
Dynamic: license-file
